XGueJ.v
// GUERRA, Jose Maria Angelo C. (S17)

`timescale 1ns / 1ps

// Module Name: Behavioral Modeling
// Boolean Function: F = (AB' + A'B) (C+D')

module behav(F,A,B,C,D);
    // Define input and output
    output reg F;
    input A,B,C,D;

    // Assign boolean function
    always @*
    begin
        F = ((A & ~B) | (~A & B)) & (C | ~D);
    end

endmodule

XGueJ_tb.v
// GUERRA, Jose Maria Angelo C. (S17)

`timescale 1ns / 1ps

// Module Name: Behavioral Modeling
// Boolean Function: F = (AB' + A'B) (C+D')

module behav_tb();
    // Declare local reg and wire identifiers
    reg[3:0] t_input;
    wire t_F;
    integer i;

    // Instantiate the design module under test
    behav dut(t_F, t_input[3], t_input[2], t_input[1], t_input[0]);

    // Generate stimulus, using initial or always statements
    initial
        begin
            t_input = 4'b0000;
            for(i = 1; i < 17; i++)
                #10 t_input = i; // Every 10ns, value 0000 becomes 0001 and so on until it goes back to 0000
        end

    // Display the output response (text or graphics (or both))
    initial
    begin
        $display("Written by Jose Maria Angelo Guerra (S17)");
        $display("F = (AB' + A'B) (C+D')");
        $display("Verilog Behavioral Model");

        $monitor("Time = %03d | A = %b B = %b C = %b D = %b | Output_F = %b",
                $time, t_input[3], t_input[2], t_input[1], t_input[0], t_F);
        $dumpfile("behav.vcd");
        $dumpvars();
    end
endmodule

behav.vcd
$date
	Tue Jun 13 02:57:40 2023
$end
$version
	Icarus Verilog
$end
$timescale
	1ps
$end
$scope module behav_tb $end
$var wire 1 ! t_F $end
$var reg 4 " t_input [3:0] $end
$var integer 32 # i [31:0] $end
$scope module dut $end
$var wire 1 $ A $end
$var wire 1 % B $end
$var wire 1 & C $end
$var wire 1 ' D $end
$var reg 1 ! F $end
$upscope $end
$upscope $end
$enddefinitions $end
#0
$dumpvars
0'
0&
0%
0$
b1 #
b0 "
0!
$end
#10000
1'
b10 #
b1 "
#20000
1&
0'
b11 #
b10 "
#30000
1'
b100 #
b11 "
#40000
1!
1%
0&
0'
b101 #
b100 "
#50000
0!
1'
b110 #
b101 "
#60000
1!
1&
0'
b111 #
b110 "
#70000
1'
b1000 #
b111 "
#80000
1$
0%
0&
0'
b1001 #
b1000 "
#90000
0!
1'
b1010 #
b1001 "
#100000
1!
1&
0'
b1011 #
b1010 "
#110000
1'
b1100 #
b1011 "
#120000
0!
1%
0&
0'
b1101 #
b1100 "
#130000
1'
b1110 #
b1101 "
#140000
1&
0'
b1111 #
b1110 "
#150000
1'
b10000 #
b1111 "
#160000
0$
0%
0&
0'
b10001 #
b0 "
